assembly_stats/__init__.py
assembly_stats/assembly_stats.py
assembly_stats/cli.py
assembly_stats-0.1.4.dist-info/LICENSE.md
assembly_stats-0.1.4.dist-info/METADATA
assembly_stats-0.1.4.dist-info/WHEEL
assembly_stats-0.1.4.dist-info/entry_points.txt
assembly_stats-0.1.4.dist-info/top_level.txt
assembly_stats-0.1.4.dist-info/RECORD
