Metadata-Version: 2.1
Name: assembly-stats
Version: 0.1.4
Summary: Calculates both scaffold and contig statistics (N50, L50, etc.) from a scaffold FASTA file.
Home-page: https://github.com/MikeTrizna/assembly_stats
Author: Mike Trizna
Author-email: triznam@si.edu
License: UNKNOWN
Platform: UNKNOWN
Classifier: Programming Language :: Python :: 3
Classifier: Operating System :: OS Independent
Classifier: License :: OSI Approved :: MIT License
Requires-Dist: numpy
